SouyunkuSpringBootCloudJiaocheng/README.md
SouyunkuSpringBootCloudJiaocheng/__init__.py
SouyunkuSpringBootCloudJiaocheng/__main__.py
SouyunkuSpringBootCloudJiaocheng/file.epub
SouyunkuSpringBootCloudJiaocheng/index.html
SouyunkuSpringBootCloudJiaocheng/css/__init__.py
SouyunkuSpringBootCloudJiaocheng/css/annotations.css
SouyunkuSpringBootCloudJiaocheng/css/main.css
SouyunkuSpringBootCloudJiaocheng/css/normalize.css
SouyunkuSpringBootCloudJiaocheng/css/popup.css
SouyunkuSpringBootCloudJiaocheng/font/__init__.py
SouyunkuSpringBootCloudJiaocheng/font/fontello.eot
SouyunkuSpringBootCloudJiaocheng/font/fontello.svg
SouyunkuSpringBootCloudJiaocheng/font/fontello.ttf
SouyunkuSpringBootCloudJiaocheng/font/fontello.woff
SouyunkuSpringBootCloudJiaocheng/img/__init__.py
SouyunkuSpringBootCloudJiaocheng/img/annotator-glyph-sprite.png
SouyunkuSpringBootCloudJiaocheng/img/annotator-icon-sprite.png
SouyunkuSpringBootCloudJiaocheng/img/apple-touch-icon.png
SouyunkuSpringBootCloudJiaocheng/img/cancelfullscreen.png
SouyunkuSpringBootCloudJiaocheng/img/close.png
SouyunkuSpringBootCloudJiaocheng/img/fullscreen.png
SouyunkuSpringBootCloudJiaocheng/img/loader.gif
SouyunkuSpringBootCloudJiaocheng/img/menu-icon.png
SouyunkuSpringBootCloudJiaocheng/img/save.png
SouyunkuSpringBootCloudJiaocheng/img/saved.png
SouyunkuSpringBootCloudJiaocheng/img/settings-s.png
SouyunkuSpringBootCloudJiaocheng/img/settings.png
SouyunkuSpringBootCloudJiaocheng/img/star.png
SouyunkuSpringBootCloudJiaocheng/js/__init__.py
SouyunkuSpringBootCloudJiaocheng/js/epub.js
SouyunkuSpringBootCloudJiaocheng/js/epub.min.js
SouyunkuSpringBootCloudJiaocheng/js/epub.min.map
SouyunkuSpringBootCloudJiaocheng/js/hooks.min.js
SouyunkuSpringBootCloudJiaocheng/js/hooks.min.map
SouyunkuSpringBootCloudJiaocheng/js/reader.js
SouyunkuSpringBootCloudJiaocheng/js/reader.js.map
SouyunkuSpringBootCloudJiaocheng/js/reader.min.js
SouyunkuSpringBootCloudJiaocheng/js/reader.min.map
SouyunkuSpringBootCloudJiaocheng/js/hooks/__init__.py
souyunku_spring_boot_cloud_jiaocheng-2024.3.3.0.dist-info/METADATA
souyunku_spring_boot_cloud_jiaocheng-2024.3.3.0.dist-info/WHEEL
souyunku_spring_boot_cloud_jiaocheng-2024.3.3.0.dist-info/entry_points.txt
souyunku_spring_boot_cloud_jiaocheng-2024.3.3.0.dist-info/top_level.txt
souyunku_spring_boot_cloud_jiaocheng-2024.3.3.0.dist-info/RECORD
